ragrid/__init__.py
ragrid/document_extractor.py
ragrid/evaluation_question_generator.py
ragrid/hub.py
ragrid/library_exceptions.py
ragrid/text_chunker.py
ragrid/text_cleaner.py
ragrid/text_utils.py
ragrid/tru_lens_evaluator.py
yajendra-1.0.1.dist-info/LICENSE
yajendra-1.0.1.dist-info/METADATA
yajendra-1.0.1.dist-info/WHEEL
yajendra-1.0.1.dist-info/top_level.txt
yajendra-1.0.1.dist-info/RECORD
