Metadata-Version: 2.1
Name: yajendra
Version: 1.0.1
Summary: This library is to search the best parameters across different steps of the RAG process.
License: MIT
Classifier: License :: OSI Approved :: MIT License
Classifier: Programming Language :: Python :: 3.9
Classifier: Programming Language :: Python :: 3.10
Classifier: Programming Language :: Python :: 3.11
License-File: LICENSE
Requires-Dist: langchain >=0.1.13
Requires-Dist: langchain-openai >=0.1.1
Requires-Dist: trulens-eval >=0.27.0
Requires-Dist: chromadb >=0.4.24
Requires-Dist: sentence-transformers >=2.6.1
Requires-Dist: unstructured[pdf] >=0.13.0
